setup.py
h_modbus/__init__.py
h_modbus.egg-info/PKG-INFO
h_modbus.egg-info/SOURCES.txt
h_modbus.egg-info/dependency_links.txt
h_modbus.egg-info/not-zip-safe
h_modbus.egg-info/top_level.txt