Metadata-Version: 1.0
Name: h-modbus
Version: 1.4
Summary: for modbus as 0x01 0x02 0x03 0x04 0x05 0x06 0x0f 0x10
Home-page: http://github.com/tongling/ab_resbase
Author: herming
Author-email: an520999@gmail.com
License: JUST
Platform: UNKNOWN
